aiomemcached/__init__.py
aiomemcached/client.py
aiomemcached/constants.py
aiomemcached/exceptions.py
aiomemcached/pool.py
AioMemcached-0.8.4.dist-info/LICENSE.txt
AioMemcached-0.8.4.dist-info/METADATA
AioMemcached-0.8.4.dist-info/WHEEL
AioMemcached-0.8.4.dist-info/top_level.txt
AioMemcached-0.8.4.dist-info/RECORD
