Metadata-Version: 2.1
Name: AioMemcached
Version: 0.8.4
Summary: A pure-Python(3.7+) asyncio memcached client, fork from aiomcache.
Author: Rex Zhang
Author-email: rex.zhang@gmail.com
License: BSD
Project-URL: homepage, https://github.com/rexzhang/aiomemcached
Project-URL: repository, https://github.com/rexzhang/aiomemcached
Project-URL: changelog, https://github.com/rexzhang/aiomemcached/blob/main/CHANGES.rst
Keywords: webdav,asgi,asyncio
Classifier: Development Status :: 4 - Beta
Classifier: Programming Language :: Python :: 3
Classifier: Framework :: AsyncIO
Classifier: Topic :: Software Development :: Libraries :: Python Modules
Requires-Python: >=3.7
License-File: LICENSE.txt
